NEMO_sensors/__init__.py
NEMO_sensors/admin.py
NEMO_sensors/api.py
NEMO_sensors/apps.py
NEMO_sensors/customizations.py
NEMO_sensors/evaluators.py
NEMO_sensors/models.py
NEMO_sensors/sensors.py
NEMO_sensors/urls.py
NEMO_sensors/views.py
NEMO_sensors/management/__init__.py
NEMO_sensors/management/commands/__init__.py
NEMO_sensors/management/commands/manage_sensor_data.py
NEMO_sensors/migrations/0001_initial.py
NEMO_sensors/migrations/0002_alter_sensor_data_label_alter_sensor_data_prefix_and_more.py
NEMO_sensors/migrations/0003_alter_sensor_options_sensor_last_read_and_more.py
NEMO_sensors/migrations/0004_sensorcard_extra_args.py
NEMO_sensors/migrations/__init__.py
NEMO_sensors/static/NEMO_sensors/chart.js
NEMO_sensors/static/NEMO_sensors/chart.min.js
NEMO_sensors/static/NEMO_sensors/chartjs-adapter-moment.js
NEMO_sensors/static/NEMO_sensors/daterangepicker.css
NEMO_sensors/static/NEMO_sensors/daterangepicker.js
NEMO_sensors/static/NEMO_sensors/sensors.css
NEMO_sensors/templates/NEMO_sensors/sensor_alerts.html
NEMO_sensors/templates/NEMO_sensors/sensor_data.html
NEMO_sensors/templates/NEMO_sensors/sensors.html
NEMO_sensors/templates/customizations/customizations_sensors.html
NEMO_sensors/tests/__init__.py
NEMO_sensors/tests/test_modbus_sensors.py
NEMO_sensors/tests/test_settings.py
nemo_sensors-1.2.0.dist-info/licenses/LICENSE
nemo_sensors-1.2.0.dist-info/METADATA
nemo_sensors-1.2.0.dist-info/WHEEL
nemo_sensors-1.2.0.dist-info/top_level.txt
nemo_sensors-1.2.0.dist-info/RECORD
