Metadata-Version: 2.4
Name: NEMO-sensors
Version: 1.2.0
Summary: Plugin for NEMO providing support for connecting to Modbus sensors
Author-email: Center for Nanoscale Science and Technology <CNSTapplications@nist.gov>
License: # NIST Software Licensing Statement
Project-URL: Homepage, https://github.com/usnistgov/NEMO-sensors
Project-URL: Changelog, https://github.com/usnistgov/NEMO-sensors/releases
Project-URL: Issues, https://github.com/usnistgov/NEMO-sensors/issues
Keywords: NEMO
Classifier: Development Status :: 5 - Production/Stable
Classifier: Environment :: Web Environment
Classifier: Intended Audience :: Science/Research
Classifier: Intended Audience :: System Administrators
Classifier: License :: Public Domain
Classifier: Natural Language :: English
Classifier: Operating System :: OS Independent
Classifier: Framework :: Django :: 4.2
Classifier: Programming Language :: Python :: 3.10
Classifier: Programming Language :: Python :: 3.11
Classifier: Programming Language :: Python :: 3.12
Classifier: Programming Language :: Python :: 3.13
Requires-Python: >=3.10
License-File: LICENSE
Requires-Dist: django
Requires-Dist: pymodbus
Provides-Extra: nemo-ce
Requires-Dist: NEMO-CE>=7.3.0; extra == "nemo-ce"
Provides-Extra: nemo
Requires-Dist: NEMO>=7.3.0; extra == "nemo"
Provides-Extra: dev-tools
Requires-Dist: pre-commit; extra == "dev-tools"
Requires-Dist: djlint; extra == "dev-tools"
Requires-Dist: black; extra == "dev-tools"
Dynamic: license-file
